neoliqpay/__init__.py
neoliqpay/async_liqpay.py
neoliqpay/core.py
neoliqpay/sync_liqpay.py
neoliqpay-3.0.0.dist-info/LICENSE
neoliqpay-3.0.0.dist-info/METADATA
neoliqpay-3.0.0.dist-info/WHEEL
neoliqpay-3.0.0.dist-info/top_level.txt
neoliqpay-3.0.0.dist-info/RECORD
