Metadata-Version: 2.1
Name: neoliqpay
Version: 3.0.0
Summary: Asyncio LiqPay SDK for Python
Author-email: LiaVa <mistickusya.2012@gmail.com>
License: MIT License        
Project-URL: Homepage, https://github.com/MiloLug/neoliqpay
Keywords: neoneoliqpay,aioliqpay,liqpay,asyncio,sdk
Classifier: License :: OSI Approved :: MIT License
Classifier: Programming Language :: Python :: 3.6
Classifier: Programming Language :: Python :: 3.7
Classifier: Programming Language :: Python :: 3.8
Classifier: Programming Language :: Python :: 3.9
Classifier: Programming Language :: Python :: 3.10
Requires-Python: >=3.6
License-File: LICENSE
Provides-Extra: async
Requires-Dist: aiohttp ; extra == 'async'
Provides-Extra: dev
Requires-Dist: black ; extra == 'dev'
Requires-Dist: bumpver ; extra == 'dev'
Requires-Dist: isort ; extra == 'dev'
Requires-Dist: pip-tools ; extra == 'dev'
Requires-Dist: pytest ; extra == 'dev'
Provides-Extra: sync
Requires-Dist: requests ; extra == 'sync'
